nnpdf/__init__.py
nnpdf-0.1.0.dist-info/WHEEL
nnpdf-0.1.0.dist-info/METADATA
nnpdf-0.1.0.dist-info/RECORD
