Metadata-Version: 2.1
Name: nnpdf
Version: 0.1.0
Summary: NNPDF ecosystem meta-package
Author: Alessandro Candido
Author-email: candido.ale@gmail.com
Requires-Python: >=3.10,<4.0
Classifier: Programming Language :: Python :: 3
Classifier: Programming Language :: Python :: 3.10
